{
  "creds": {
    "noiseKey": {
      "private": {
        "type": "Buffer",
        "data": "OA+vCP4V1rDEH8fr/h6oxWMvZUr5wmdnZ3gDn91w5Es="
      },
      "public": {
        "type": "Buffer",
        "data": "BB/ovBPoDQx89i/IczCpW0WQpQIN0OJtS+MaSUX3KzQ="
      }
    },
    "signedIdentityKey": {
      "private": {
        "type": "Buffer",
        "data": "0JEn7l0A7UU/5OdK7Q60jl5GS/n3g22thU67ZMs3KFk="
      },
      "public": {
        "type": "Buffer",
        "data": "qrfH5VQ/f3zEBfbf+4fr7MBjODTOz7ryaKo1UMW0WhY="
      }
    },
    "signedPreKey": {
      "keyPair": {
        "private": {
          "type": "Buffer",
          "data": "oCMVyYJ1avwwd4ZnPc32rl/8zc8wOOodI1mR/hENqm4="
        },
        "public": {
          "type": "Buffer",
          "data": "etJM8eK+Z/FQPBJwUPy/y5p3Pchy4s5Wxm42vmdcOx8="
        }
      },
      "signature": {
        "type": "Buffer",
        "data": "kkzN6LSB0ApfuFu60fYJXQVp2l3Ej6d3TCaLxClQL4mBBrR70V02LVPVGDM0A3dswgvyKqZnl2oqdLe/uUZ2iw=="
      },
      "keyId": 1
    },
    "registrationId": 160,
    "advSecretKey": "+Q1t9dyN5MD5Sex1hl4PrkqWdeolnhKvZ0N8IdoVJGk=",
    "processedHistoryMessages": [
      {
        "key": {
          "remoteJid": "14015948752@s.whatsapp.net",
          "fromMe": true,
          "id": "3AC06242D08D3FC090B8"
        },
        "timestamp": 1662190660
      },
      {
        "key": {
          "remoteJid": "14015948752@s.whatsapp.net",
          "fromMe": true,
          "id": "3AEC2BF1F9D787C93784"
        },
        "timestamp": 1662190662
      }
    ],
    "nextPreKeyId": 31,
    "firstUnuploadedPreKeyId": 31,
    "accountSettings": {
      "unarchiveChats": false
    },
    "account": {
      "details": "CLikzqsJEMKIzJgGGAE=",
      "accountSignature": "4riW3J8tKTBR5ZaYArvj4ucpzDUX88xSoaHDWUh7PSnesfY9EOpnQrZuTYD76kutWkifcxz3bsSIIHGA5Ddzhw==",
      "deviceSignature": "1sZVLkJZhjmnq7nd5v9xjrHqqNXlut9xAuapb6pFD9SZ3wUqdQQ9S9SNBK6/YUetZN1NK1eocEtdMiRLY1Gkhg=="
    },
    "me": {
      "id": "14015948752:1@s.whatsapp.net",
      "name": "HMR BOT"
    },
    "signalIdentities": [
      {
        "identifier": {
          "name": "14015948752:1@s.whatsapp.net",
          "deviceId": 0
        },
        "identifierKey": {
          "type": "Buffer",
          "data": "BW625odJm4VM23TX6+wLujP3qmCwLzCADszd6lfOPelW"
        }
      }
    ],
    "platform": "iphone",
    "lastAccountSyncTimestamp": 1662190660,
    "myAppStateKeyId": "AAAAADUY"
  },
  "keys": {
    "preKeys": {
      "1": {
        "private": {
          "type": "Buffer",
          "data": "qBTzSWLadjtr63axd8Jo8r7vukudUnIJi58TRKLBqlI="
        },
        "public": {
          "type": "Buffer",
          "data": "sKPZWw0Epe7jCpJOfEVKUprHEiyVh6BWoetbRKgRYQ8="
        }
      },
      "2": null,
      "3": {
        "private": {
          "type": "Buffer",
          "data": "6GO2O/typv43YwuSw34lwiRmAQRSVtyODCqff9gky3k="
        },
        "public": {
          "type": "Buffer",
          "data": "Jf5MlG9qCB+GdSsn8AbusGENEW6eSXK3u3cXnAM1qXo="
        }
      },
      "4": {
        "private": {
          "type": "Buffer",
          "data": "2DPSb6kLxfOaxjOY9kl898apJ51Tzd9rNFn9NusI3GA="
        },
        "public": {
          "type": "Buffer",
          "data": "POEMWxulkQfhMzSmtO4i9fh4Bx44nElinyTMp8iMtWE="
        }
      },
      "5": {
        "private": {
          "type": "Buffer",
          "data": "QApX//LC7wb0PT3MCLL1TOB3GNsBbGbuFz7Q1STg13U="
        },
        "public": {
          "type": "Buffer",
          "data": "PpojVwOJahgRcr4ajKdJnCs7ytXZMpfVnbPbNaZp8zM="
        }
      },
      "6": {
        "private": {
          "type": "Buffer",
          "data": "iBc0XwKmGyB5ZJ/ZmRWUzF7X1Gv7ouaQT/cmlrs2Yn0="
        },
        "public": {
          "type": "Buffer",
          "data": "IHOENUU2qyDLqKQqnrZt3QBxP5vuacWMjO7xgJk82X8="
        }
      },
      "7": {
        "private": {
          "type": "Buffer",
          "data": "2LHNAcYBknjUlfncVKDhO2QRduQqaLxpRbd4SCTXKHc="
        },
        "public": {
          "type": "Buffer",
          "data": "6Ai/SduMqVoN4lwkRYr2bdOCYw1fJt+KMjRTShsmmjA="
        }
      },
      "8": {
        "private": {
          "type": "Buffer",
          "data": "KBw1Ir0F3XQQqLDCUZoDTtEu6GSEwheu6xWgXLIi0nU="
        },
        "public": {
          "type": "Buffer",
          "data": "71kSSAI2VWBl6Fl3QTkqa3+tXd6QivtIccEnFrKsUDg="
        }
      },
      "9": {
        "private": {
          "type": "Buffer",
          "data": "wOyZ7FaKxU+JZYFq5tgfGMtub7q9c2qQgvGI/9Vwk14="
        },
        "public": {
          "type": "Buffer",
          "data": "EAqwcFh4Uv7DhYtzbslqLXUpXLjIisNIihU0AKxQZHQ="
        }
      },
      "10": {
        "private": {
          "type": "Buffer",
          "data": "qPpKNS+CqYmxWOplzi8wVIEfr4hZBXSISIxdq9rkP1I="
        },
        "public": {
          "type": "Buffer",
          "data": "6jO+ir+sqKc7IuBqjnoTT17V7Uas4UZWcP+eBJZTdSM="
        }
      },
      "11": {
        "private": {
          "type": "Buffer",
          "data": "6ATZfrJe5NzIIq2Hnd13Dy5e1bCRSZwapcu9Xun160s="
        },
        "public": {
          "type": "Buffer",
          "data": "TGhaoF9Hk5qMur8YJjDZfulgGiyf5BWBF0gMQLAThUc="
        }
      },
      "12": {
        "private": {
          "type": "Buffer",
          "data": "YFT+nDoMmlGLwFEwrGfhQThjCwsyVAJbfhBvX13v+1E="
        },
        "public": {
          "type": "Buffer",
          "data": "akte90RfoLuOgPPNkA5xRxefxxcORpJzZ7nRloY81FE="
        }
      },
      "13": {
        "private": {
          "type": "Buffer",
          "data": "WNs/iFjJt/otr8K5ZPQ0xGTY0erSwjxoZ6GLzkfC1V0="
        },
        "public": {
          "type": "Buffer",
          "data": "9iLltJv0qlai1AkIlQr53/aiB9tittG+muvgh3g3fFg="
        }
      },
      "14": {
        "private": {
          "type": "Buffer",
          "data": "+AWxRQe/qLImttpw196Ett/l9Fqu/bnXK3cdgd3Os30="
        },
        "public": {
          "type": "Buffer",
          "data": "Obng1AKHQMT+ZNDADQVZqufqG8zHKI0R3NboIZXY/BM="
        }
      },
      "15": {
        "private": {
          "type": "Buffer",
          "data": "gL5PlteN3sv5GRu1R6F8xk7rDHrH4GQas37ZTFNnQW4="
        },
        "public": {
          "type": "Buffer",
          "data": "c7inVSOfeMKyzZyBlPlDeazA+90Z52EK8v7040RKlRg="
        }
      },
      "16": {
        "private": {
          "type": "Buffer",
          "data": "MGsMsDKsgsps4yce1WvJh97ieQHmJ9MdIRNtS6ZfGFU="
        },
        "public": {
          "type": "Buffer",
          "data": "YOjOKhXjeZvVNXRgJ8tFrt9xfVjT1k8yRGyA/2XqPUM="
        }
      },
      "17": {
        "private": {
          "type": "Buffer",
          "data": "wE4E9hmtgUte5L05+GaZfJeo4seRPg3+0yBSh4UGAG8="
        },
        "public": {
          "type": "Buffer",
          "data": "sMsdCCMQ/F3C9cWoViOBHad25pG6OQx/uOuVVYq14Us="
        }
      },
      "18": {
        "private": {
          "type": "Buffer",
          "data": "YC5i+R+Uk3vtAr8ummiRpVCEKNNVEtxIsyswSaArlmk="
        },
        "public": {
          "type": "Buffer",
          "data": "6JDxOhQMVgnvQmYV3C4gvSD2IzXKUGk3JfsUBz6HlTY="
        }
      },
      "19": {
        "private": {
          "type": "Buffer",
          "data": "mKDZYLrWNRhZ9g5m2kgdZtXdWy+yIWMy2OOLU+skwW4="
        },
        "public": {
          "type": "Buffer",
          "data": "LBDDXX8DJ/4bpQ8RevMYFgkF+37cAswoQ5iLF1T+SnQ="
        }
      },
      "20": {
        "private": {
          "type": "Buffer",
          "data": "yOBKYBYxVeAU7Irzkui2sMMmMaEj+lfAk96+QT2ZhmI="
        },
        "public": {
          "type": "Buffer",
          "data": "vy2WHwMhLE+mGSNq7pKzEg5yrePNH0cVBcJMOld5vxo="
        }
      },
      "21": {
        "private": {
          "type": "Buffer",
          "data": "+PFmlwg1t6WP7HE/CjZdy7zWSkMFCGki7KKFk1EK7F4="
        },
        "public": {
          "type": "Buffer",
          "data": "LYUqJk2pi2UF8oOIePwrH5Qiuz8QLEdAahokkMO5+24="
        }
      },
      "22": {
        "private": {
          "type": "Buffer",
          "data": "8K1DSKhsV2NRtDKxLxnCzdSUPYbmQ36poVGkaZMes1Q="
        },
        "public": {
          "type": "Buffer",
          "data": "4J5cRUR4Vk0tM09s2jqNZBj/rTPjJEcOVy9Vnk40V1I="
        }
      },
      "23": {
        "private": {
          "type": "Buffer",
          "data": "2G6i+2hGyf/nhW8qbGNVKG8jaWfj6/HgXQkqUhRHVm4="
        },
        "public": {
          "type": "Buffer",
          "data": "DgDBBGdgeY3UXncxGw6RR0GRzqTklqKEcL+eEw9T9Ag="
        }
      },
      "24": {
        "private": {
          "type": "Buffer",
          "data": "KPMENrf/Ns2VhHqmvaOCgsGEGPVG2bkE+y0LFmf4H1Q="
        },
        "public": {
          "type": "Buffer",
          "data": "dvlaeWaNnVkv4jIsB+KGI+UQAyt6G3hmzSfnCcl1Vn0="
        }
      },
      "25": {
        "private": {
          "type": "Buffer",
          "data": "KOpOPYN62gBmvNQqCie1e/+z26dJLTK0K/mSZa/bpXE="
        },
        "public": {
          "type": "Buffer",
          "data": "AxlqGLvKbo09bDNuG4O9Pnpkq6xpTG6z6LpGqh92KhU="
        }
      },
      "26": {
        "private": {
          "type": "Buffer",
          "data": "aLRwZQwU09GonCjT3sGcW6Tes7/d55ZMEi5+4DNUTnk="
        },
        "public": {
          "type": "Buffer",
          "data": "ujaFfH6qdDd9Fym4+vbFGPILqUh/9o8QfGknFz/PlW8="
        }
      },
      "27": {
        "private": {
          "type": "Buffer",
          "data": "mHx4Zo2czJW5hbSQA/Kf1+nbv9vDo+CUEQBGytCKwGc="
        },
        "public": {
          "type": "Buffer",
          "data": "iktES4OMRBnFkWU59+InmxdxTDtYuKQpcxlItq38Gx0="
        }
      },
      "28": {
        "private": {
          "type": "Buffer",
          "data": "6OCyCZzELzES/bf9QZRboUCefPICsdn0B/R7hzyeIGU="
        },
        "public": {
          "type": "Buffer",
          "data": "ZCnvSPGeEkwxoZbtDeamTBgNxN54synv4f1lh0y3tCs="
        }
      },
      "29": {
        "private": {
          "type": "Buffer",
          "data": "SJbIv0FhW4oRUn0fq6MPGgpH8QmO78H/z8EjKmdO0l4="
        },
        "public": {
          "type": "Buffer",
          "data": "3Uwt1js1Ocxvki/gd3RWQe4iew00TTKpvff8UQJhqjk="
        }
      },
      "30": {
        "private": {
          "type": "Buffer",
          "data": "mLCRQT8MW4G6sT1e4qmrTgrqEyRV65zfGIkvUXylVHU="
        },
        "public": {
          "type": "Buffer",
          "data": "SeH5TRHGa5zJyzNZU6/SqoAB51x+0QGUVA396o7PaUg="
        }
      }
    },
    "sessions": {
      "14015948752.0": {
        "_sessions": {
          "Bd/EfKl1aUxJfBS7juNfcg6ZEx+uSBYGZQkVE1BX8iJR": {
            "registrationId": 854172096,
            "currentRatchet": {
              "ephemeralKeyPair": {
                "pubKey": "BZ+kh2aD5M4l7TW0dxxOJ/KQ7WgMRIBUCLQd2MHv4V99",
                "privKey": "GPJuj5IeLUlzdE+T1eh880MhH1ADvafhxfydCIUV+0s="
              },
              "lastRemoteEphemeralKey": "BZnU09Z8xTA2ql9QqAp9A8RsDIZ4MRMcY8j445fW8VIc",
              "previousCounter": 0,
              "rootKey": "KmJDIFTRSYrVfo/9kD2iGAfUAVcmPnRkD+ysjB16UeA="
            },
            "indexInfo": {
              "baseKey": "Bd/EfKl1aUxJfBS7juNfcg6ZEx+uSBYGZQkVE1BX8iJR",
              "baseKeyType": 2,
              "closed": -1,
              "used": 1662190661245,
              "created": 1662190661245,
              "remoteIdentityKey": "BW625odJm4VM23TX6+wLujP3qmCwLzCADszd6lfOPelW"
            },
            "_chains": {
              "BZnU09Z8xTA2ql9QqAp9A8RsDIZ4MRMcY8j445fW8VIc": {
                "chainKey": {
                  "counter": 4,
                  "key": "RWLJz1rGXpaStIh3fi1diFo+qnVMj/OvVojy+ob4fWg="
                },
                "chainType": 2,
                "messageKeys": {}
              },
              "BZ+kh2aD5M4l7TW0dxxOJ/KQ7WgMRIBUCLQd2MHv4V99": {
                "chainKey": {
                  "counter": -1,
                  "key": "sAhU4ptCYwNe8pKOGwydELe9KrSdh9eL/AuUVnPWxPo="
                },
                "chainType": 1,
                "messageKeys": {}
              }
            }
          }
        },
        "version": "v1"
      }
    },
    "appStateSyncKeys": {
      "AAAAADUY": {
        "keyData": "aclSVu5umtqFqo0kizvlIcJGYmAGMIV42s6uYQbOuW8=",
        "fingerprint": {
          "rawId": 2507379256,
          "currentIndex": 1,
          "deviceIndexes": [
            1,
            0
          ]
        },
        "timestamp": "1662190660253"
      }
    },
    "appStateVersions": {
      "critical_block": {
        "version": 2,
        "hash": {
          "type": "Buffer",
          "data": "aHcrhabvTL7guYMRz7djRwH7qcNu659JeGjFtEJl9+ftfoFOxWKnPld1sfUogUA6fB+iTc24xnm8Jhc0ep+3/fCZE5ckW626MheYSN8egF+Gz5uuXv8jUiHvBkBabgTFBt+OwdfCWaHOxOUlXgETUwyzVvCd5PPkYNYZSn1/pAU="
        },
        "indexValueMap": {
          "kSPqFQTLzh5hbCGk2Oo/TtHL5fQaq0ntk6qtBhiSrWQ=": {
            "valueMac": {
              "type": "Buffer",
              "data": "qZ4SARt8e85g6ja4uw9HY6ogwbDFlwhZNUjFF1A8cSA="
            }
          },
          "jq3wPdtsqE8TeC98rEeFegVnujW8+uno9RKLir3EhE8=": {
            "valueMac": {
              "type": "Buffer",
              "data": "48XCKsIbHQdXYinTDrIiYsXdya4SJm2ZYpTwkmDu7DM="
            }
          }
        }
      }
    }
  }
}